Metadata-Version: 2.1
Name: django-network-field
Version: 0.1
Requires-Dist: Django
